plotkit/__init__.py
plotkit/const.py
plotkit/file.py
plotkit/headless.py
plotkit/plotkit.py
plotkit/rasterize.py
plotkit/style.py
mplotkit-0.4.0.dist-info/LICENSE
mplotkit-0.4.0.dist-info/METADATA
mplotkit-0.4.0.dist-info/WHEEL
mplotkit-0.4.0.dist-info/top_level.txt
mplotkit-0.4.0.dist-info/RECORD
