Metadata-Version: 2.1
Name: mplotkit
Version: 0.4.0
Summary: Collection of helpers for plotting with matplotlib
Home-page: https://github.com/martok/py-plotkit
Author: Martok
Author-email: martok@martoks-place.de
License: MIT
Project-URL: Bug Tracker, https://github.com/martok/py-plotkit/issues
Classifier: Development Status :: 5 - Production/Stable
Classifier: License :: OSI Approved :: MIT License
Classifier: Operating System :: OS Independent
Classifier: Framework :: Matplotlib
Classifier: Intended Audience :: Science/Research
Classifier: Intended Audience :: Developers
Classifier: Topic :: Scientific/Engineering :: Visualization
Requires-Python: >=3.6
License-File: LICENSE
Requires-Dist: matplotlib
